{
    "schema_version": "1.0",
    "id": "f3f3eef1d2100200e593",
    "category": "kernel",
    "version": "7b4f2bc91c15fdcf948bb2d9741a9d7d54303f8d",
    "trigger": {
        "poc": "https://syzkaller.appspot.com/text?tag=ReproC&x=128b1d53180000",
        "guide": "gcc poc.c -lpthread -static -o poc\n./scptovm poc\nif ! grep -q 'bash -l' connectvm; then\n\tsed -i '$s/$/ \"echo executing poc...; \\.\\/poc; bash -l\"/' connectvm\nfi\n./connectvm",
        "bzImage": "https://storage.googleapis.com/syzbot-assets/c02d1542e886/bzImage-7b4f2bc9.xz",
        "configfile": "https://syzkaller.appspot.com/text?tag=KernelConfig&x=ae644165a243bf62"
    }
}